free_google_SERP_api
