Metadata-Version: 2.1
Name: free-google-SERP-api
Version: 1.0.4
Summary: Una librería Python para extraer y manipular los diferentes datos de los resultados de las búsquedas de Google
Home-page: https://twitter.com/seo_torch
Author: Dídac Anton
Author-email: dinerofacil.x.paypal@gmail.com
Classifier: Topic :: Software Development :: Libraries :: Python Modules
Classifier: Topic :: Utilities
Classifier: Development Status :: 5 - Production/Stable
Classifier: Operating System :: MacOS
Classifier: Operating System :: Microsoft
Classifier: Programming Language :: Python :: 3.6
Classifier: Programming Language :: Python :: 3.7
Classifier: Programming Language :: Python :: 3.8
Classifier: Typing :: Typed
Requires-Python: >=3.6
